cogito/__init__.py
cogito/_version.py
cogito/cli.py
cogito/exceptions.py
cogito/api/__init__.py
cogito/api/handlers.py
cogito/api/responses.py
cogito/commands/__init__.py
cogito/commands/config.py
cogito/commands/initialize.py
cogito/commands/predict.py
cogito/commands/run.py
cogito/commands/scaffold.py
cogito/commands/train.py
cogito/commands/version.py
cogito/core/__init__.py
cogito/core/app.py
cogito/core/exceptioin_handlers.py
cogito/core/exceptions.py
cogito/core/logging.py
cogito/core/metrics.py
cogito/core/model_store.py
cogito/core/models.py
cogito/core/utils.py
cogito/core/config/__init__.py
cogito/core/config/file.py
cogito/core/config/v0/__init__.py
cogito/core/config/v0/base.py
cogito/core/config/v0/fastapi.py
cogito/core/config/v0/route.py
cogito/core/config/v0/server.py
cogito/core/config/v1/__init__.py
cogito/core/config/v1/base.py
cogito/core/config/v1/fastapi.py
cogito/core/config/v1/route.py
cogito/core/config/v1/server.py
cogito/lib/__init__.py
cogito/lib/prediction.py
cogito/lib/training.py
cogito/lib/version.py
cogito/templates/predict_class_template.jinja2
cogito/templates/train_class_template.jinja2
cogito-0.3.1.dist-info/licenses/LICENSE
cogito-0.3.1.dist-info/METADATA
cogito-0.3.1.dist-info/WHEEL
cogito-0.3.1.dist-info/entry_points.txt
cogito-0.3.1.dist-info/top_level.txt
cogito-0.3.1.dist-info/RECORD
